{
  "ticker": "EQIX",
  "savedAt": "2026-02-10T15:00:00.324Z",
  "tradingDay": "2026-02-10",
  "data": {
    "contracts": [
      {
        "strike_price": 600,
        "contract_type": "call",
        "open_interest": 1,
        "greeks": {
          "delta": 0.9761992115743379,
          "gamma": 0.0003459988306229563,
          "theta": -0.4388960887479404,
          "vega": 0.06128158701483266
        },
        "implied_volatility": 1.1186194722004152,
        "expiry": "2026-02-20"
      },
      {
        "strike_price": 620,
        "contract_type": "call",
        "open_interest": 0,
        "greeks": {
          "delta": 0.9756974693648828,
          "gamma": 0.0003877948817252747,
          "theta": -0.40694330040466875,
          "vega": 0.06228063754941695
        },
        "implied_volatility": 1.0142678695301635,
        "expiry": "2026-02-20"
      },
      {
        "strike_price": 630,
        "contract_type": "call",
        "open_interest": 0,
        "greeks": {
          "delta": 0.9741976576909942,
          "gamma": 0.0004242013803757006,
          "theta": -0.415681559213088,
          "vega": 0.06277943741108663
        },
        "implied_volatility": 0.9792512098325571,
        "expiry": "2026-02-20"
      },
      {
        "strike_price": 640,
        "contract_type": "call",
        "open_interest": 0,
        "greeks": {
          "delta": 0.9745487010569444,
          "gamma": 0.0004446521348477712,
          "theta": -0.3872365565438241,
          "vega": 0.0632612200475429
        },
        "implied_volatility": 0.9210709062280376,
        "expiry": "2026-02-20"
      },
      {
        "strike_price": 650,
        "contract_type": "call",
        "open_interest": 0,
        "greeks": {
          "delta": 0.9764524215295451,
          "gamma": 0.00044867611529276287,
          "theta": -0.3339858754006912,
          "vega": 0.06372970428545288
        },
        "implied_volatility": 0.848093785248184,
        "expiry": "2026-02-20"
      },
      {
        "strike_price": 660,
        "contract_type": "call",
        "open_interest": 0,
        "greeks": {
          "delta": 0.9676138690827915,
          "gamma": 0.000577103048212107,
          "theta": -0.4397400854450015,
          "vega": 0.128453375219849
        },
        "implied_volatility": 0.861408307282839,
        "expiry": "2026-02-20"
      },
      {
        "strike_price": 670,
        "contract_type": "call",
        "open_interest": 0,
        "greeks": {
          "delta": 0.9634289695208259,
          "gamma": 0.0006593150525032256,
          "theta": -0.4687581698710724,
          "vega": 0.12943335357495353
        },
        "implied_volatility": 0.8321211958749403,
        "expiry": "2026-02-20"
      },
      {
        "strike_price": 680,
        "contract_type": "call",
        "open_interest": 0,
        "greeks": {
          "delta": 0.9654714583254584,
          "gamma": 0.0006810693376469644,
          "theta": -0.41601830757694674,
          "vega": 0.13037120093480267
        },
        "implied_volatility": 0.7687638369067264,
        "expiry": "2026-02-20"
      },
      {
        "strike_price": 690,
        "contract_type": "call",
        "open_interest": 1,
        "greeks": {
          "delta": 0.9555729495623337,
          "gamma": 0.0008406494227290133,
          "theta": -0.5086231681091706,
          "vega": 0.1313676301923336
        },
        "implied_volatility": 0.7672500037210657,
        "expiry": "2026-02-20"
      },
      {
        "strike_price": 700,
        "contract_type": "call",
        "open_interest": 5,
        "greeks": {
          "delta": 0.9518885788707102,
          "gamma": 0.0009429187070639307,
          "theta": -0.519467234107986,
          "vega": 0.13232338514449452
        },
        "implied_volatility": 0.7317562093491828,
        "expiry": "2026-02-20"
      },
      {
        "strike_price": 710,
        "contract_type": "call",
        "open_interest": 0,
        "greeks": {
          "delta": 0.9493728168402576,
          "gamma": 0.0010453329334497929,
          "theta": -0.5121353124957666,
          "vega": 0.13326142015187553
        },
        "implied_volatility": 0.6892776051916331,
        "expiry": "2026-02-20"
      },
      {
        "strike_price": 720,
        "contract_type": "call",
        "open_interest": 0,
        "greeks": {
          "delta": 0.9607373681294381,
          "gamma": 0.0009895571838487752,
          "theta": -0.35940393362964584,
          "vega": 0.13405696842349316
        },
        "implied_volatility": 0.5877656175275058,
        "expiry": "2026-02-20"
      },
      {
        "strike_price": 730,
        "contract_type": "call",
        "open_interest": 0,
        "greeks": {
          "delta": 0.9514750199573963,
          "gamma": 0.0012120275431579946,
          "theta": -0.4156619783776077,
          "vega": 0.13502537232252174
        },
        "implied_volatility": 0.5728226276958384,
        "expiry": "2026-02-20"
      },
      {
        "strike_price": 740,
        "contract_type": "call",
        "open_interest": 2,
        "greeks": {
          "delta": 0.9252585375034781,
          "gamma": 0.0016131949516243688,
          "theta": -0.6120182880145502,
          "vega": 0.2350863118140332
        },
        "implied_volatility": 0.6072441588048839,
        "expiry": "2026-02-20"
      },
      {
        "strike_price": 750,
        "contract_type": "call",
        "open_interest": 5,
        "greeks": {
          "delta": 0.9162827195388002,
          "gamma": 0.001864487781557119,
          "theta": -0.6265855276407397,
          "vega": 0.2366747126956643
        },
        "implied_volatility": 0.5714347940601895,
        "expiry": "2026-02-20"
      },
      {
        "strike_price": 760,
        "contract_type": "call",
        "open_interest": 3,
        "greeks": {
          "delta": 0.9030457279115803,
          "gamma": 0.0021882748378361213,
          "theta": -0.6669095782349201,
          "vega": 0.238288908228323
        },
        "implied_volatility": 0.5445146952488102,
        "expiry": "2026-02-20"
      },
      {
        "strike_price": 770,
        "contract_type": "call",
        "open_interest": 14,
        "greeks": {
          "delta": 0.8765233022204806,
          "gamma": 0.0026100310306009654,
          "theta": -0.8138503301123835,
          "vega": 0.36005768250846387
        },
        "implied_volatility": 0.5523782148818909,
        "expiry": "2026-02-20"
      },
      {
        "strike_price": 780,
        "contract_type": "call",
        "open_interest": 9,
        "greeks": {
          "delta": 0.8583852024116297,
          "gamma": 0.0030395245978993755,
          "theta": -0.8260182596325175,
          "vega": 0.3624275136724765
        },
        "implied_volatility": 0.5156785102894859,
        "expiry": "2026-02-20"
      },
      {
        "strike_price": 790,
        "contract_type": "call",
        "open_interest": 51,
        "greeks": {
          "delta": 0.8299886250543986,
          "gamma": 0.0035549178666567775,
          "theta": -0.8916640809074973,
          "vega": 0.3648948914306282
        },
        "implied_volatility": 0.4959204473495526,
        "expiry": "2026-02-20"
      },
      {
        "strike_price": 800,
        "contract_type": "call",
        "open_interest": 62,
        "greeks": {
          "delta": 0.7960449621034474,
          "gamma": 0.004119267746012645,
          "theta": -0.9840529795365159,
          "vega": 0.3674229976451274
        },
        "implied_volatility": 0.4845997744501545,
        "expiry": "2026-02-20"
      },
      {
        "strike_price": 810,
        "contract_type": "call",
        "open_interest": 51,
        "greeks": {
          "delta": 0.7508086111217241,
          "gamma": 0.004621579833898711,
          "theta": -1.0821452926491566,
          "vega": 0.4838147599912032
        },
        "implied_volatility": 0.4804099717845008,
        "expiry": "2026-02-20"
      },
      {
        "strike_price": 820,
        "contract_type": "call",
        "open_interest": 27,
        "greeks": {
          "delta": 0.7025479807040844,
          "gamma": 0.005137046272264011,
          "theta": -1.159243261822983,
          "vega": 0.487135022486612
        },
        "implied_volatility": 0.47210197244904295,
        "expiry": "2026-02-20"
      },
      {
        "strike_price": 830,
        "contract_type": "call",
        "open_interest": 21,
        "greeks": {
          "delta": 0.65252364152737,
          "gamma": 0.005684997400841287,
          "theta": -1.2176758857461227,
          "vega": 0.5605292283283249
        },
        "implied_volatility": 0.4603125490122808,
        "expiry": "2026-02-20"
      },
      {
        "strike_price": 840,
        "contract_type": "call",
        "open_interest": 30,
        "greeks": {
          "delta": 0.595269639375322,
          "gamma": 0.006138387764146331,
          "theta": -1.2078677150112365,
          "vega": 0.5643294397845302
        },
        "implied_volatility": 0.4414081995597142,
        "expiry": "2026-02-20"
      },
      {
        "strike_price": 850,
        "contract_type": "call",
        "open_interest": 32,
        "greeks": {
          "delta": 0.5329412063112597,
          "gamma": 0.006590349293038831,
          "theta": -1.2079493757133735,
          "vega": 0.5682000492445042
        },
        "implied_volatility": 0.4262795612959655,
        "expiry": "2026-02-20"
      },
      {
        "strike_price": 860,
        "contract_type": "call",
        "open_interest": 19,
        "greeks": {
          "delta": 0.46736510907762174,
          "gamma": 0.0066937770020581875,
          "theta": -1.168745163215761,
          "vega": 0.5720939338488051
        },
        "implied_volatility": 0.41627004813799723,
        "expiry": "2026-02-20"
      },
      {
        "strike_price": 870,
        "contract_type": "call",
        "open_interest": 40,
        "greeks": {
          "delta": 0.3994758691600074,
          "gamma": 0.006648748016852234,
          "theta": -1.1172016444695494,
          "vega": 0.5760154364148508
        },
        "implied_volatility": 0.4085900675208824,
        "expiry": "2026-02-20"
      },
      {
        "strike_price": 880,
        "contract_type": "call",
        "open_interest": 67,
        "greeks": {
          "delta": 0.30911659323155516,
          "gamma": 0.00704588624187881,
          "theta": -0.8670427885716647,
          "vega": 0.5079853164166301
        },
        "implied_volatility": 0.3496130597002993,
        "expiry": "2026-02-20"
      },
      {
        "strike_price": 890,
        "contract_type": "call",
        "open_interest": 79,
        "greeks": {
          "delta": 0.27578235367586884,
          "gamma": 0.005833898945752681,
          "theta": -0.9439725757903802,
          "vega": 0.5108522501272538
        },
        "implied_volatility": 0.40131057237070195,
        "expiry": "2026-02-20"
      },
      {
        "strike_price": 900,
        "contract_type": "call",
        "open_interest": 9,
        "greeks": {
          "delta": 0.18649947867648325,
          "gamma": 0.005418831319937523,
          "theta": -0.6496247698386832,
          "vega": 0.3939553212740055
        },
        "implied_volatility": 0.34542046878963356,
        "expiry": "2026-02-20"
      },
      {
        "strike_price": 910,
        "contract_type": "call",
        "open_interest": 5,
        "greeks": {
          "delta": 0.17359859192753505,
          "gamma": 0.004538025860450459,
          "theta": -0.7089396743469636,
          "vega": 0.395888398879518
        },
        "implied_volatility": 0.3945837090479216,
        "expiry": "2026-02-20"
      },
      {
        "strike_price": 920,
        "contract_type": "call",
        "open_interest": 3,
        "greeks": {
          "delta": 0.13442267443636452,
          "gamma": 0.0038376054099476973,
          "theta": -0.609623916426864,
          "vega": 0.26560795148953287
        },
        "implied_volatility": 0.39803654112281617,
        "expiry": "2026-02-20"
      },
      {
        "strike_price": 930,
        "contract_type": "call",
        "open_interest": 2,
        "greeks": {
          "delta": 0.12877102473689836,
          "gamma": 0.003346441303245726,
          "theta": -0.652752647240996,
          "vega": 0.2668813947294845
        },
        "implied_volatility": 0.44123383599604693,
        "expiry": "2026-02-20"
      },
      {
        "strike_price": 600,
        "contract_type": "put",
        "open_interest": 0,
        "greeks": {
          "delta": -0.01773020855840505,
          "gamma": 0.00029054242553087315,
          "theta": -0.313647280576325,
          "vega": 0.06116966380248349
        },
        "implied_volatility": 1.0420559754036787,
        "expiry": "2026-02-20"
      },
      {
        "strike_price": 620,
        "contract_type": "put",
        "open_interest": 1,
        "greeks": {
          "delta": -0.019224356160843555,
          "gamma": 0.0003392662446398902,
          "theta": -0.30947933734338817,
          "vega": 0.06219858887583035
        },
        "implied_volatility": 0.9580375448064246,
        "expiry": "2026-02-20"
      },
      {
        "strike_price": 630,
        "contract_type": "put",
        "open_interest": 0,
        "greeks": {
          "delta": -0.016330851462589568,
          "gamma": 0.0003210147244505889,
          "theta": -0.24543918651662855,
          "vega": 0.06269066383637842
        },
        "implied_volatility": 0.8771900702873757,
        "expiry": "2026-02-20"
      },
      {
        "strike_price": 640,
        "contract_type": "put",
        "open_interest": 0,
        "greeks": {
          "delta": -0.019434185159448118,
          "gamma": 0.0003809176313766917,
          "theta": -0.2805079632432407,
          "vega": 0.0631985509803
        },
        "implied_volatility": 0.8609292086393867,
        "expiry": "2026-02-20"
      },
      {
        "strike_price": 650,
        "contract_type": "put",
        "open_interest": 4,
        "greeks": {
          "delta": -0.019523993035785156,
          "gamma": 0.00040462498731578785,
          "theta": -0.2660114331050016,
          "vega": 0.06368785673502232
        },
        "implied_volatility": 0.8135301302492528,
        "expiry": "2026-02-20"
      },
      {
        "strike_price": 660,
        "contract_type": "put",
        "open_interest": 15,
        "greeks": {
          "delta": -0.02993639343767157,
          "gamma": 0.0005574707148705645,
          "theta": -0.4008917552250888,
          "vega": 0.1284334766514447
        },
        "implied_volatility": 0.8508701229907759,
        "expiry": "2026-02-20"
      },
      {
        "strike_price": 670,
        "contract_type": "put",
        "open_interest": 65,
        "greeks": {
          "delta": -0.07188713411454432,
          "gamma": 0.0009137316801303742,
          "theta": -0.9930456921630223,
          "vega": 0.2236365243836563
        },
        "implied_volatility": 1.0459413081722717,
        "expiry": "2026-02-20"
      },
      {
        "strike_price": 680,
        "contract_type": "put",
        "open_interest": 3,
        "greeks": {
          "delta": -0.05141630265255471,
          "gamma": 0.0008501270088533737,
          "theta": -0.6378526394495885,
          "vega": 0.13044964251176192
        },
        "implied_volatility": 0.86922945567229,
        "expiry": "2026-02-20"
      },
      {
        "strike_price": 690,
        "contract_type": "put",
        "open_interest": 2,
        "greeks": {
          "delta": -0.029676627650845725,
          "gamma": 0.0006756827983877424,
          "theta": -0.3271277367163855,
          "vega": 0.13128136183394948
        },
        "implied_volatility": 0.6983803678188337,
        "expiry": "2026-02-20"
      },
      {
        "strike_price": 700,
        "contract_type": "put",
        "open_interest": 2033,
        "greeks": {
          "delta": -0.03444574937348658,
          "gamma": 0.0007916536972478481,
          "theta": -0.35248661326395436,
          "vega": 0.1322344747454207
        },
        "implied_volatility": 0.6698368547611913,
        "expiry": "2026-02-20"
      },
      {
        "strike_price": 710,
        "contract_type": "put",
        "open_interest": 29,
        "greeks": {
          "delta": -0.07535152309340713,
          "gamma": 0.0012435548754694047,
          "theta": -0.7830261137691994,
          "vega": 0.23037668820700566
        },
        "implied_volatility": 0.7965573631112204,
        "expiry": "2026-02-20"
      },
      {
        "strike_price": 720,
        "contract_type": "put",
        "open_interest": 39,
        "greeks": {
          "delta": -0.03968331604371014,
          "gamma": 0.001004425036527153,
          "theta": -0.34866661907171914,
          "vega": 0.13407315989125743
        },
        "implied_volatility": 0.591622625471041,
        "expiry": "2026-02-20"
      },
      {
        "strike_price": 730,
        "contract_type": "put",
        "open_interest": 14,
        "greeks": {
          "delta": -0.061404191006452814,
          "gamma": 0.001361480931148551,
          "theta": -0.5360661148893183,
          "vega": 0.2334650636143097
        },
        "implied_volatility": 0.630105511460566,
        "expiry": "2026-02-20"
      },
      {
        "strike_price": 740,
        "contract_type": "put",
        "open_interest": 23,
        "greeks": {
          "delta": -0.06074895789989463,
          "gamma": 0.0014899884386482805,
          "theta": -0.48117048888512814,
          "vega": 0.13635579808105663
        },
        "implied_volatility": 0.5707696955210115,
        "expiry": "2026-02-20"
      },
      {
        "strike_price": 750,
        "contract_type": "put",
        "open_interest": 2017,
        "greeks": {
          "delta": -0.09219881350842306,
          "gamma": 0.0019302828957416514,
          "theta": -0.6818383781761539,
          "vega": 0.23677321134607282
        },
        "implied_volatility": 0.5970598192922503,
        "expiry": "2026-02-20"
      },
      {
        "strike_price": 760,
        "contract_type": "put",
        "open_interest": 39,
        "greeks": {
          "delta": -0.09433801497366677,
          "gamma": 0.002175923007784573,
          "theta": -0.6258851184145521,
          "vega": 0.23828165488395803
        },
        "implied_volatility": 0.5389327001237048,
        "expiry": "2026-02-20"
      },
      {
        "strike_price": 770,
        "contract_type": "put",
        "open_interest": 86,
        "greeks": {
          "delta": -0.11323964625991519,
          "gamma": 0.002579509641275253,
          "theta": -0.7019936704379308,
          "vega": 0.23995915736633205
        },
        "implied_volatility": 0.5243176112337917,
        "expiry": "2026-02-20"
      },
      {
        "strike_price": 780,
        "contract_type": "put",
        "open_interest": 48,
        "greeks": {
          "delta": -0.1330735613807352,
          "gamma": 0.003030965673839863,
          "theta": -0.7478639658907972,
          "vega": 0.36236301477725696
        },
        "implied_volatility": 0.49940504491750326,
        "expiry": "2026-02-20"
      },
      {
        "strike_price": 790,
        "contract_type": "put",
        "open_interest": 12,
        "greeks": {
          "delta": -0.16319304633397835,
          "gamma": 0.003569728094201403,
          "theta": -0.8201352992120472,
          "vega": 0.3648510934660268
        },
        "implied_volatility": 0.48209498456991284,
        "expiry": "2026-02-20"
      },
      {
        "strike_price": 800,
        "contract_type": "put",
        "open_interest": 29,
        "greeks": {
          "delta": -0.2048692407444521,
          "gamma": 0.004112583691207772,
          "theta": -0.9682542852931756,
          "vega": 0.3675722489722327
        },
        "implied_volatility": 0.4881543850905245,
        "expiry": "2026-02-20"
      },
      {
        "strike_price": 810,
        "contract_type": "put",
        "open_interest": 9,
        "greeks": {
          "delta": -0.2415620635749085,
          "gamma": 0.004728666652889686,
          "theta": -1.0029865287367281,
          "vega": 0.48377827451593186
        },
        "implied_volatility": 0.4635957284471526,
        "expiry": "2026-02-20"
      },
      {
        "strike_price": 820,
        "contract_type": "put",
        "open_interest": 13,
        "greeks": {
          "delta": -0.29189957834211866,
          "gamma": 0.0052684146467940575,
          "theta": -1.0829375392895155,
          "vega": 0.4871368481826599
        },
        "implied_volatility": 0.45663480347156393,
        "expiry": "2026-02-20"
      },
      {
        "strike_price": 830,
        "contract_type": "put",
        "open_interest": 1,
        "greeks": {
          "delta": -0.33751786149219287,
          "gamma": 0.006110715910495623,
          "theta": -1.0877860833056152,
          "vega": 0.49145118099372387
        },
        "implied_volatility": 0.4252643780033839,
        "expiry": "2026-02-20"
      },
      {
        "strike_price": 840,
        "contract_type": "put",
        "open_interest": 1,
        "greeks": {
          "delta": -0.40020452741047213,
          "gamma": 0.006536457032613062,
          "theta": -1.1010052470969913,
          "vega": 0.5643704090680216
        },
        "implied_volatility": 0.4141046469671949,
        "expiry": "2026-02-20"
      },
      {
        "strike_price": 850,
        "contract_type": "put",
        "open_interest": 0,
        "greeks": {
          "delta": -0.4668019815985798,
          "gamma": 0.0068503498317951115,
          "theta": -1.1330566773996393,
          "vega": 0.5682953719670732
        },
        "implied_volatility": 0.41074722922473994,
        "expiry": "2026-02-20"
      },
      {
        "strike_price": 860,
        "contract_type": "put",
        "open_interest": 2,
        "greeks": {
          "delta": -0.5320540693972785,
          "gamma": 0.006633863401101301,
          "theta": -1.149858156316719,
          "vega": 0.5721492315499518
        },
        "implied_volatility": 0.42093332105980924,
        "expiry": "2026-02-20"
      },
      {
        "strike_price": 870,
        "contract_type": "put",
        "open_interest": 2,
        "greeks": {
          "delta": -0.6048601446052678,
          "gamma": 0.006867027881536023,
          "theta": -1.048698579311801,
          "vega": 0.575846859878443
        },
        "implied_volatility": 0.3959801662692218,
        "expiry": "2026-02-20"
      },
      {
        "strike_price": 880,
        "contract_type": "put",
        "open_interest": 0,
        "greeks": {
          "delta": -0.670709566752741,
          "gamma": 0.006522906718278389,
          "theta": -0.9633142712860384,
          "vega": 0.5075154058030006
        },
        "implied_volatility": 0.39034282780429524,
        "expiry": "2026-02-20"
      },
      {
        "strike_price": 890,
        "contract_type": "put",
        "open_interest": 0,
        "greeks": {
          "delta": -0.7329044281794186,
          "gamma": 0.005981289395555467,
          "theta": -0.8676573783045209,
          "vega": 0.5097308921694603
        },
        "implied_volatility": 0.3880395497349304,
        "expiry": "2026-02-20"
      },
      {
        "strike_price": 900,
        "contract_type": "put",
        "open_interest": 0,
        "greeks": {
          "delta": -0.7768094123376795,
          "gamma": 0.005244111679098338,
          "theta": -0.8188179713640866,
          "vega": 0.3927929513286781
        },
        "implied_volatility": 0.40352366687640195,
        "expiry": "2026-02-20"
      },
      {
        "strike_price": 910,
        "contract_type": "put",
        "open_interest": 1,
        "greeks": {
          "delta": -0.8439484724520062,
          "gamma": 0.004563956787386095,
          "theta": -0.5967323139067887,
          "vega": 0.39187467392099173
        },
        "implied_volatility": 0.3726764692388242,
        "expiry": "2026-02-20"
      },
      {
        "strike_price": 920,
        "contract_type": "put",
        "open_interest": 0,
        "greeks": {
          "delta": -0.8873373203131876,
          "gamma": 0.0037458223229670197,
          "theta": -0.45691059562450687,
          "vega": 0.26369768566305607
        },
        "implied_volatility": 0.3638125705135052,
        "expiry": "2026-02-20"
      },
      {
        "strike_price": 930,
        "contract_type": "put",
        "open_interest": 0,
        "greeks": {
          "delta": -0.9249514395023515,
          "gamma": 0.002891123078766243,
          "theta": -0.32977355866830704,
          "vega": 0.254937066938443
        },
        "implied_volatility": 0.3578800222147418,
        "expiry": "2026-02-20"
      }
    ],
    "expiry": "2026-02-20",
    "spot": 849.73
  }
}